gnu_pass_to_csv/__init__.py
gnu_pass_to_csv/main.py
gnu_pass_to_csv-1.0.5.dist-info/LICENSE
gnu_pass_to_csv-1.0.5.dist-info/METADATA
gnu_pass_to_csv-1.0.5.dist-info/WHEEL
gnu_pass_to_csv-1.0.5.dist-info/entry_points.txt
gnu_pass_to_csv-1.0.5.dist-info/RECORD
