Metadata-Version: 2.1
Name: gnu-pass-to-csv
Version: 1.0.5
Summary: Convert GNU pass password store to CSV
Home-page: https://gitlab.com/fbossiere/gnu-pass-to-csv.git
License: MIT
Author: Francois Bossiere
Author-email: francois.bossiere@protonmail.com
Requires-Python: >=3.12,<4.0
Classifier: Development Status :: 5 - Production/Stable
Classifier: Intended Audience :: Developers
Classifier: License :: OSI Approved :: MIT License
Classifier: Operating System :: OS Independent
Classifier: Programming Language :: Python :: 3
Classifier: Programming Language :: Python :: 3.12
Classifier: Topic :: Utilities
Requires-Dist: loguru (>=0.7.2,<0.8.0)
Requires-Dist: pandas (>=2.2.2,<3.0.0)
Requires-Dist: python-dotenv (>=1.0.1,<2.0.0)
Requires-Dist: typer (>=0.12.4,<0.13.0)
Project-URL: Repository, https://gitlab.com/fbossiere/gnu-pass-to-csv.git
